celesto/__init__.py
celesto/a2a.py
celesto/deployment.py
celesto/main.py
celesto/proxy.py
celesto/sdk/__init__.py
celesto/sdk/client.py
celesto/sdk/exceptions.py
celesto/sdk/types.py
celesto-0.0.2.dist-info/METADATA
celesto-0.0.2.dist-info/WHEEL
celesto-0.0.2.dist-info/entry_points.txt
celesto-0.0.2.dist-info/licenses/LICENSE
celesto-0.0.2.dist-info/RECORD
