Metadata-Version: 2.4
Name: celesto
Version: 0.0.2
Summary: Python SDK and CLI for the Celesto AI platform.
Project-URL: Homepage, https://celesto.ai
Project-URL: Documentation, https://docs.celesto.ai/celesto-sdk
Project-URL: Repository, https://github.com/CelestoAI/sdk
Project-URL: Source Code, https://github.com/CelestoAI/sdk
Project-URL: Issue Tracker, https://github.com/CelestoAI/sdk/issues
Project-URL: Changelog, https://github.com/CelestoAI/sdk/releases
Author-email: Aniket Maurya <aniket@celesto.ai>
Maintainer-email: Aniket Maurya <aniket@celesto.ai>
License-Expression: Apache-2.0
License-File: LICENSE
Keywords: agent-deployment,agents,ai,ai-platform,api,celesto,delegated-access,deployment,gatekeeper,google-drive,oauth,sdk
Classifier: Development Status :: 4 - Beta
Classifier: Intended Audience :: Developers
Classifier: License :: OSI Approved :: Apache Software License
Classifier: Operating System :: OS Independent
Classifier: Programming Language :: Python
Classifier: Programming Language :: Python :: 3
Classifier: Programming Language :: Python :: 3 :: Only
Classifier: Programming Language :: Python :: 3.10
Classifier: Programming Language :: Python :: 3.11
Classifier: Programming Language :: Python :: 3.12
Classifier: Programming Language :: Python :: 3.13
Classifier: Topic :: Internet :: WWW/HTTP
Classifier: Topic :: Scientific/Engineering :: Artificial Intelligence
Classifier: Topic :: Software Development :: Libraries :: Python Modules
Classifier: Typing :: Typed
Requires-Python: >=3.10
Requires-Dist: a2a-sdk>=0.3.10
Requires-Dist: fastmcp>=2.7.1
Requires-Dist: httpx>=0.27.0
Requires-Dist: python-dotenv>=1.0.0
Requires-Dist: rich>=14.0.0
Requires-Dist: typer>=0.20.0
Requires-Dist: typing-extensions>=4.10.0
